__init__.py
rotas_brasil_python_sdk-1.0.0.dist-info/licenses/LICENSE
rotasbrasil/__init__.py
rotasbrasil/api.py
rotasbrasil/apis/__init__.py
rotasbrasil/apis/rotas.py
rotasbrasil/dtos/__init__.py
rotasbrasil/dtos/rota.py
rotas_brasil_python_sdk-1.0.0.dist-info/METADATA
rotas_brasil_python_sdk-1.0.0.dist-info/WHEEL
rotas_brasil_python_sdk-1.0.0.dist-info/top_level.txt
rotas_brasil_python_sdk-1.0.0.dist-info/RECORD
