Metadata-Version: 2.4
Name: rotas-brasil-python-sdk
Version: 1.0.0
Summary: Client de comunicaçao c/ API do Rotas Brasil
Author-email: Filipe Coelho <filipe@fmconsult.com.br>
License: MIT License
Project-URL: Homepage, https://github.com/seuuser/minha-biblioteca
Project-URL: Bug Tracker, https://github.com/seuuser/minha-biblioteca/issues
Keywords: sdk,api,fmconsult
Classifier: Programming Language :: Python :: 3
Classifier: License :: OSI Approved :: MIT License
Classifier: Operating System :: OS Independent
Requires-Python: >=3.11
License-File: LICENSE
Dynamic: license-file
